setup.py
digHeightWeightExtractor/__init__.py
digHeightWeightExtractor/height_weight_extractor.py
digHeightWeightExtractor/hw_helper.py
digHeightWeightExtractor.egg-info/PKG-INFO
digHeightWeightExtractor.egg-info/SOURCES.txt
digHeightWeightExtractor.egg-info/dependency_links.txt
digHeightWeightExtractor.egg-info/requires.txt
digHeightWeightExtractor.egg-info/top_level.txt
test/__init__.py
test/test_groundtruth.py
test/test_height_weight_extractor.py
test/test_hw_helper.py
test/groundtruth/__init__.py