Metadata-Version: 1.1
Name: digHeightWeightExtractor
Version: 0.3.0
Summary: digHeightWeightExtractor
Home-page: https://github.com/ZwEin27/dig-phone-extractor
Author: Lingzhe Teng
Author-email: zwein27@gmail.com
License: UNKNOWN
Download-URL: https://github.com/ZwEin27/dig-phone-extractor
Keywords: height,weight,extractor
Platform: UNKNOWN
